zenodo_deposit/__init__.py
zenodo_deposit/api.py
zenodo_deposit/cli.py
zenodo_deposit/config.py
zenodo_deposit/metadata.py
zenodo_deposit/py.typed
zenodo_deposit-0.1.5.dist-info/METADATA
zenodo_deposit-0.1.5.dist-info/WHEEL
zenodo_deposit-0.1.5.dist-info/entry_points.txt
zenodo_deposit-0.1.5.dist-info/licenses/LICENSE
zenodo_deposit-0.1.5.dist-info/RECORD
