Metadata-Version: 2.4
Name: zenodo-deposit
Version: 0.1.5
Summary: Zenodo deposit tool
Author-email: Will Fitzgerald <willf@users.noreply.github.com>
License-File: LICENSE
Requires-Python: >=3.13
Requires-Dist: backoff>=2.2.1
Requires-Dist: click>=8.1.7
Requires-Dist: pytest>=8.3.4
Requires-Dist: requests>=2.32.3
Requires-Dist: rich>=13.9.4
